{
  "seattle": 733919,
  "spokane": 229071,
  "spokane valley": 105905,
  "sammamish": 66630,
  "shoreline": 57918,
  "seatac": 30759,
  "sunnyside": 16346,
  "snoqualmie": 13810,
  "sedro-woolley": 12509,
  "shelton": 10763,
  "sumner": 10673,
  "snohomish": 10154,
  "stanwood": 8438,
  "sequim": 8241,
  "selah": 8208,
  "steilacoom": 6721,
  "sultan": 5604,
  "south bend": 1760,
  "soap lake": 1706,
  "sumas": 1629,
  "stevenson": 1573,
  "st. john": 594,
  "south cle elum": 549,
  "sprague": 520,
  "south prairie": 369,
  "spangle": 286,
  "springdale": 243,
  "skykomish": 159,
  "starbuck": 124
}