{
  "mccook": 7356,
  "minden": 3111,
  "madison": 2216,
  "milford": 2145,
  "mitchell": 1526,
  "mariettaship": 937,
  "morrill village": 930,
  "mirageship": 893,
  "minatare": 720,
  "madisonship": 650,
  "mead village": 626,
  "mullen village": 511,
  "murray village": 489,
  "malcolm village": 475,
  "mccool junction village": 466,
  "marbleship": 465,
  "mariposaship": 386,
  "morse bluffship": 380,
  "midlandship": 361,
  "merna village": 345,
  "mapleship": 318,
  "monroe village": 287,
  "meadow grove village": 278,
  "murdock village": 274,
  "maywood village": 270,
  "maxwell village": 256,
  "milligan village": 241,
  "madrid village": 237,
  "marquette village": 237,
  "montereyship": 190,
  "meadship": 178,
  "manley village": 171,
  "mortonship": 163,
  "millership": 154,
  "mason city village": 148,
  "miller village": 131,
  "mayship": 124,
  "monroeship": 124,
  "morse bluff village": 119,
  "marionship": 115,
  "melbeta village": 112,
  "memphis village": 110,
  "myrtleship": 98,
  "mcculleyship": 97,
  "malmo village": 95,
  "merriman village": 88,
  "martinsburg village": 78,
  "maconship": 73,
  "michiganship": 70,
  "merryship": 66,
  "mcgrew village": 64,
  "milburnship": 63,
  "momenceship": 63,
  "maskell village": 60,
  "marshallship": 54,
  "mcclureship": 48,
  "magnet village": 46,
  "mclean village": 37,
  "moorefield village": 26,
  "mullenship": 21,
  "monowi village": 0
}